Adafruit_PCA9685/PCA9685.py
Adafruit_PCA9685/__init__.py
Adafruit_PCA9685-1.0.1.dist-info/metadata.json
Adafruit_PCA9685-1.0.1.dist-info/METADATA
Adafruit_PCA9685-1.0.1.dist-info/RECORD
Adafruit_PCA9685-1.0.1.dist-info/WHEEL
Adafruit_PCA9685-1.0.1.dist-info/DESCRIPTION.rst
Adafruit_PCA9685-1.0.1.dist-info/dependency_links.txt
Adafruit_PCA9685-1.0.1.dist-info/top_level.txt
