Metadata-Version: 1.1
Name: Adafruit_PCA9685
Version: 1.0.1
Summary: Python code to use the PCA9685 PWM servo/LED controller with a Raspberry Pi or BeagleBone Black.
Home-page: https://github.com/adafruit/Adafruit_Python_PCA9685/
Author: Tony DiCola
Author-email: tdicola@adafruit.com
License: MIT
Platform: UNKNOWN
Classifier: Development Status :: 4 - Beta
Classifier: Operating System :: POSIX :: Linux
Classifier: License :: OSI Approved :: MIT License
Classifier: Intended Audience :: Developers
Classifier: Programming Language :: Python :: 2.7
Classifier: Programming Language :: Python :: 3
Classifier: Topic :: Software Development
Classifier: Topic :: System :: Hardware
